sekf/__init__.py
sekf/config.py
sekf/functions.py
sekf/modeling.py
sekf/optimizers.py
sekf/utils.py
sekf/viz.py
sekf-0.0.3.dist-info/METADATA
sekf-0.0.3.dist-info/WHEEL
sekf-0.0.3.dist-info/licenses/LICENSE
sekf-0.0.3.dist-info/RECORD
